{    
    "todos:1": {
        "userId": 1,
        "id": 1,
        "title": "delectus aut autem",
        "completed": false
    },
    "todos:2": {
        "userId": 1,
        "id": 2,
        "title": "quis ut nam facilis et officia qui",
        "completed": false
    },
    "todos:3": {
        "userId": 2,
        "id": 3,
        "title": "fugiat veniam minus",
        "completed": true
    },
    "todos:4": {
        "userId": 2,
        "id": 4,
        "title": "et porro tempora",
        "completed": false
    },
    "todos:5": {
        "userId": 3,
        "id": 5,
        "title": "laboriosam mollitia et enim quasi adipisci quia provident illum",
        "completed": true
    },
    "todos:6": {
        "userId": 3,
        "id": 6,
        "title": "qui ullam ratione quibusdam voluptatem quia omnis",
        "completed": false
    },
    "todos:7": {
        "userId": 4,
        "id": 7,
        "title": "illo expedita consequatur quia in",
        "completed": false
    },
    "todos:8": {
        "userId": 4,
        "id": 8,
        "title": "quo adipisci enim quam ut ab",
        "completed": true
    },
    "todos:9": {
        "userId": 5,
        "id": 9,
        "title": "molestiae perspiciatis ipsa",
        "completed": false
    },
    "todos:10": {
        "userId": 5,
        "id": 10,
        "title": "illo est ratione doloremque quia maiores aut",
        "completed": true
    },
    "todos:11": {
        "userId": 6,
        "id": 11,
        "title": "vero rerum temporibus dolor",
        "completed": true
    },
    "todos:12": {
        "userId": 6,
        "id": 12,
        "title": "ipsa repellendus fugit nisi",
        "completed": true
    },
    "todos:13": {
        "userId": 7,
        "id": 13,
        "title": "et doloremque nulla",
        "completed": false
    },
    "todos:14": {
        "userId": 7,
        "id": 14,
        "title": "repellendus sunt dolores architecto voluptatum",
        "completed": true
    },
    "todos:15": {
        "userId": 8,
        "id": 15,
        "title": "ab voluptatum amet voluptas",
        "completed": true
    },
    "todos:16": {
        "userId": 8,
        "id": 16,
        "title": "accusamus eos facilis sint et aut voluptatem",
        "completed": true
    },
    "todos:17": {
        "userId": 9,
        "id": 17,
        "title": "quo laboriosam deleniti aut qui",
        "completed": false
    },
    "todos:18": {
        "userId": 9,
        "id": 18,
        "title": "dolorum est consequatur ea mollitia in culpa",
        "completed": false
    },
    "todos:19": {
        "userId": 10,
        "id": 19,
        "title": "molestiae ipsa aut voluptatibus pariatur dolor nihil",
        "completed": true
    },
    "todos:20": {
        "userId": 10,
        "id": 20,
        "title": "ullam nobis libero sapiente ad optio sint",
        "completed": true
    },
    "todos:21": {
        "userId": 11,
        "id": 21,
        "title": "suscipit repellat esse quibusdam voluptatem incidunt",
        "completed": false
    },
    "todos:22": {
        "userId": 11,
        "id": 22,
        "title": "distinctio vitae autem nihil ut molestias quo",
        "completed": true
    },
    "todos:23": {
        "userId": 12,
        "id": 23,
        "title": "et itaque necessitatibus maxime molestiae qui quas velit",
        "completed": false
    },
    "todos:24": {
        "userId": 12,
        "id": 24,
        "title": "adipisci non ad dicta qui amet quaerat doloribus ea",
        "completed": false
    },
    "todos:25": {
        "userId": 13,
        "id": 25,
        "title": "voluptas quo tenetur perspiciatis explicabo natus",
        "completed": true
    },
    "todos:26": {
        "userId": 13,
        "id": 26,
        "title": "aliquam aut quasi",
        "completed": true
    },
    "todos:27": {
        "userId": 14,
        "id": 27,
        "title": "veritatis pariatur delectus",
        "completed": false
    },
    "todos:28": {
        "userId": 14,
        "id": 28,
        "title": "nesciunt totam sit blanditiis sit",
        "completed": false
    },
    "todos:29": {
        "userId": 15,
        "id": 29,
        "title": "laborum aut in quam",
        "completed": true
    },
    "todos:30": {
        "userId": 15,
        "id": 30,
        "title": "nemo perspiciatis repellat ut dolor libero commodi blanditiis omnis",
        "completed": true
    },
    "todos:31": {
        "userId": 16,
        "id": 31,
        "title": "repudiandae totam in est sint facere fuga",
        "completed": false
    },
    "todos:32": {
        "userId": 16,
        "id": 32,
        "title": "earum doloribus ea doloremque quis",
        "completed": false
    },
    "todos:33": {
        "userId": 17,
        "id": 33,
        "title": "sint sit facilis nam ipsum",
        "completed": true
    },
    "todos:34": {
        "userId": 17,
        "id": 34,
        "title": "sed ab consequatur",
        "completed": true
    },
    "todos:35": {
        "userId": 18,
        "id": 35,
        "title": "non sunt delectus illo nulla tenetur enim omnis",
        "completed": false
    },
    "todos:36": {
        "userId": 18,
        "id": 36,
        "title": "excepturi optio reprehenderit voluptates maxime molestiae qui quas velit",
        "completed": false
    },
    "todos:37": {
        "userId": 19,
        "id": 37,
        "title": "saepe velit consequatur pariatur iure ratione",
        "completed": true
    },
    "todos:38": {
        "userId": 19,
        "id": 38,
        "title": "quia et suscipit",
        "completed": true
    },
    "todos:39": {
        "userId": 20,
        "id": 39,
        "title": "voluptatibus reiciendis iure",
        "completed": false
    },
    "todos:40": {
        "userId": 20,
        "id": 40,
        "title": "illum minima dicta",
        "completed": true
    },
    "todos:41": {
            "userId": 21,
            "id": 41,
            "title": "odit optio omnis qui sunt",
            "completed": true
        },
        "todos:42": {
            "userId": 21,
            "id": 42,
            "title": "et placeat et tempore aspernatur sint numquam",
            "completed": false
        },
        "todos:43": {
            "userId": 22,
            "id": 43,
            "title": "doloribus quod soluta",
            "completed": true
        },
        "todos:44": {
            "userId": 22,
            "id": 44,
            "title": "quas fugiat ut perspiciatis vero provident",
            "completed": false
        },
        "todos:45": {
            "userId": 23,
            "id": 45,
            "title": "quisquam id culpa",
            "completed": true
        },
        "todos:46": {
            "userId": 23,
            "id": 46,
            "title": "aut quasi autem molestiae",
            "completed": false
        },
        "todos:47": {
            "userId": 24,
            "id": 47,
            "title": "vitae aut excepturi laboriosam sint aliquam et est",
            "completed": true
        },
        "todos:48": {
            "userId": 24,
            "id": 48,
            "title": "similique nobis dolor nisi non",
            "completed": false
        },
        "todos:49": {
            "userId": 25,
            "id": 49,
            "title": "tempore non deserunt et",
            "completed": true
        },
        "todos:50": {
            "userId": 25,
            "id": 50,
            "title": "totam atque quo nesciunt",
            "completed": false
        },
        "todos:51": {
            "userId": 26,
            "id": 51,
            "title": "aliquid impedit minus velit",
            "completed": true
        },
        "todos:52": {
            "userId": 26,
            "id": 52,
            "title": "quia atque aliquam sunt impedit voluptatum rerum assumenda",
            "completed": false
        },
        "todos:53": {
            "userId": 27,
            "id": 53,
            "title": "cupiditate quos possimus corporis quisquam exercitationem beatae",
            "completed": true
        },
        "todos:54": {
            "userId": 27,
            "id": 54,
            "title": "sed et ea eum",
            "completed": false
        },
        "todos:55": {
            "userId": 28,
            "id": 55,
            "title": "ipsa dolores vel facilis ut",
            "completed": true
        },
        "todos:56": {
            "userId": 28,
            "id": 56,
            "title": "sequi quae est et qui qui eveniet asperiores",
            "completed": false
        },
        "todos:57": {
            "userId": 29,
            "id": 57,
            "title": "quia distinctio quas magnam voluptatum aut",
            "completed": true
        },
        "todos:58": {
            "userId": 29,
            "id": 58,
            "title": "doloremque saepe quia accusamus debitis dolores",
            "completed": false
        },
        "todos:59": {
            "userId": 30,
            "id": 59,
            "title": "consequatur animi dolorem saepe repellendus",
            "completed": true
        },
        "todos:60": {
            "userId": 30,
            "id": 60,
            "title": "rerum non quia dolore",
            "completed": false
        },
        "todos:61": {
            "userId": 31,
            "id": 61,
            "title": "doloremque illum aliquid cupiditate",
            "completed": true
        },
        "todos:62": {
            "userId": 31,
            "id": 62,
            "title": "voluptas sint rerum est",
            "completed": false
        },
        "todos:63": {
            "userId": 32,
            "id": 63,
            "title": "saepe eos adipisci",
            "completed": true
        },
        "todos:64": {
            "userId": 32,
            "id": 64,
            "title": "rerum quia aperiam",
            "completed": false
        },
        "todos:65": {
            "userId": 33,
            "id": 65,
            "title": "perferendis et sint",
            "completed": true
        },
        "todos:66": {
            "userId": 33,
            "id": 66,
            "title": "sit autem consequatur est",
            "completed": false
        },
        "todos:67": {
            "userId": 34,
            "id": 67,
            "title": "magnam necessitatibus",
            "completed": true
        },
        "todos:68": {
            "userId": 34,
            "id": 68,
            "title": "suscipit minus est facere",
            "completed": false
        },
        "todos:69": {
            "userId": 35,
            "id": 69,
            "title": "facilis animi ducimus",
            "completed": true
        },
        "todos:70": {
            "userId": 35,
            "id": 70,
            "title": "rerum ex veniam mollitia dolorem",
            "completed": false
        },
        "todos:71": {
            "userId": 36,
            "id": 71,
            "title": "repudiandae voluptatum quaerat",
            "completed": true
        },
        "todos:72": {
            "userId": 36,
            "id": 72,
            "title": "placeat atque fuga atque",
            "completed": false
        },
        "todos:73": {
            "userId": 37,
            "id": 73,
            "title": "consequatur cupiditate ad",
            "completed": true
        },
        "todos:74": {
            "userId": 37,
            "id": 74,
            "title": "veniam laborum deserunt",
            "completed": false
        },
        "todos:75": {
            "userId": 38,
            "id": 75,
            "title": "eveniet molestiae facere",
            "completed": true
        },
        "todos:76": {
            "userId": 38,
            "id": 76,
            "title": "magnam atque magni inventore expedita",
            "completed": false
        },
        "todos:77": {
            "userId": 39,
            "id": 77,
            "title": "neque voluptatibus corporis",
            "completed": true
        },
        "todos:78": {
            "userId": 39,
            "id": 78,
            "title": "eveniet quasi suscipit",
            "completed": false
        },
        "todos:79": {
            "userId": 40,
            "id": 79,
            "title": "velit exercitationem non",
            "completed": true
        },
        "todos:80": {
            "userId": 40,
            "id": 80,
            "title": "exercitationem maxime",
            "completed": false
        },
        "todos:81": {
            "userId": 41,
            "id": 81,
            "title": "voluptatum nihil quia voluptas",
            "completed": true
        },
        "todos:82": {
            "userId": 41,
            "id": 82,
            "title": "aperiam consequatur laboriosam",
            "completed": false
        },
        "todos:83": {
            "userId": 42,
            "id": 83,
            "title": "magnam fugiat pariatur",
            "completed": true
        },
        "todos:84": {
            "userId": 42,
            "id": 84,
            "title": "possimus illum autem",
            "completed": false
        },
        "todos:85": {
            "userId": 43,
            "id": 85,
            "title": "doloribus voluptatem",
            "completed": true
        },
        "todos:86": {
            "userId": 43,
            "id": 86,
            "title": "recusandae provident ea",
            "completed": false
        },
        "todos:87": {
            "userId": 44,
            "id": 87,
            "title": "asperiores reiciendis optio",
            "completed": true
        },
        "todos:88": {
            "userId": 44,
            "id": 88,
            "title": "laboriosam expedita",
            "completed":false
        }
}